{
  "Norman Y. Mineta San Jo": {
    "coord": [
      "37.3736", 
      "-121.942"
    ], 
    "pollution": 2595
  }, 
  "Tulelake Muni": {
    "coord": [
      "41.8874", 
      "-121.359"
    ], 
    "pollution": 32
  }, 
  "Colusa County": {
    "coord": [
      "39.1790", 
      "-121.993"
    ], 
    "pollution": 66
  }, 
  "Benton Field": {
    "coord": [
      "40.5749", 
      "-122.408"
    ], 
    "pollution": 87
  }, 
  "Westover Field Amador C": {
    "coord": [
      "38.3768", 
      "-120.794"
    ], 
    "pollution": 55
  }, 
  "Murray Field": {
    "coord": [
      "40.8034", 
      "-124.113"
    ], 
    "pollution": 172
  }, 
  "Apple Valley": {
    "coord": [
      "34.5753", 
      "-117.186"
    ], 
    "pollution": 93
  }, 
  "Rialto Muni / Miro Field": {
    "coord": [
      "34.1294", 
      "-117.402"
    ], 
    "pollution": 78
  }, 
  "Oroville Muni": {
    "coord": [
      "39.4878", 
      "-121.622"
    ], 
    "pollution": 93
  }, 
  "Independence": {
    "coord": [
      "36.8138", 
      "-118.205"
    ], 
    "pollution": 7
  }, 
  "San Carlos": {
    "coord": [
      "37.5119", 
      "-122.250"
    ], 
    "pollution": 442
  }, 
  "Metropolitan Oakland In": {
    "coord": [
      "37.7190", 
      "-122.241"
    ], 
    "pollution": 4042
  }, 
  "Lodi": {
    "coord": [
      "38.2024", 
      "-121.268"
    ], 
    "pollution": 76
  }, 
  "WARD FIELD": {
    "coord": [
      "41.8456", 
      "-123.985"
    ], 
    "pollution": 5
  }, 
  "Corcoran": {
    "coord": [
      "36.1025", 
      "-119.595"
    ], 
    "pollution": 14
  }, 
  "MONTAGUE-YREKA ROHRER FIELD": {
    "coord": [
      "41.7304", 
      "-122.546"
    ], 
    "pollution": 14
  }, 
  "Big Bear City": {
    "coord": [
      "34.2636", 
      "-116.854"
    ], 
    "pollution": 87
  }, 
  "San Nicolas Island": {
    "coord": [
      "33.2397", 
      "-119.458"
    ], 
    "pollution": 211
  }, 
  "PATTERSON": {
    "coord": [
      "37.4685", 
      "-121.169"
    ], 
    "pollution": 34
  }, 
  "ROY WILLIAMS": {
    "coord": [
      "34.1542", 
      "-116.252"
    ], 
    "pollution": 16
  }, 
  "Needles": {
    "coord": [
      "34.7662", 
      "-114.623"
    ], 
    "pollution": 26
  }, 
  "Shelter Cove": {
    "coord": [
      "40.0276", 
      "-124.073"
    ], 
    "pollution": 26
  }, 
  "PEBBLY BEACH": {
    "coord": [
      "33.3384", 
      "-118.312"
    ], 
    "pollution": 31
  }, 
  "San Diego Intl-Lindberg": {
    "coord": [
      "32.7359", 
      "-117.205"
    ], 
    "pollution": 3797
  }, 
  "LAKE WOHLFORD RESORT": {
    "coord": [
      "33.1861", 
      "-117.002"
    ], 
    "pollution": 12
  }, 
  "Hanford Muni": {
    "coord": [
      "36.3185", 
      "-119.629"
    ], 
    "pollution": 74
  }, 
  "Little River": {
    "coord": [
      "39.2620", 
      "-123.754"
    ], 
    "pollution": 16
  }, 
  "Whiteman": {
    "coord": [
      "34.2592", 
      "-118.413"
    ], 
    "pollution": 205
  }, 
  "Blythe": {
    "coord": [
      "33.6192", 
      "-114.717"
    ], 
    "pollution": 63
  }, 
  "Cable": {
    "coord": [
      "34.1117", 
      "-117.687"
    ], 
    "pollution": 250
  }, 
  "Ontario Airport": {
    "coord": [
      "34.0561", 
      "-117.601"
    ], 
    "pollution": 2096
  }, 
  "Compton / Woodley": {
    "coord": [
      "33.8900", 
      "-118.244"
    ], 
    "pollution": 172
  }, 
  "Brawley Muni": {
    "coord": [
      "32.9931", 
      "-115.517"
    ], 
    "pollution": 124
  }, 
  "Chico Muni": {
    "coord": [
      "39.8033", 
      "-121.864"
    ], 
    "pollution": 187
  }, 
  "Calexico Intl": {
    "coord": [
      "32.6695", 
      "-115.513"
    ], 
    "pollution": 31
  }, 
  "Pine Mountain Lake": {
    "coord": [
      "37.8617", 
      "-120.178"
    ], 
    "pollution": 79
  }, 
  "RANCHAERO": {
    "coord": [
      "39.7196", 
      "-121.871"
    ], 
    "pollution": 13
  }, 
  "Chino": {
    "coord": [
      "33.9744", 
      "-117.636"
    ], 
    "pollution": 409
  }, 
  "Scott Valley": {
    "coord": [
      "41.5582", 
      "-122.855"
    ], 
    "pollution": 21
  }, 
  "COUNTY OF SAN LUIS OBISPO-OCEANO AIRPORT": {
    "coord": [
      "35.1024", 
      "-120.625"
    ], 
    "pollution": 26
  }, 
  "RICHVALE": {
    "coord": [
      "39.4977", 
      "-121.771"
    ], 
    "pollution": 19
  }, 
  "Tehachapi Muni": {
    "coord": [
      "35.1350", 
      "-118.439"
    ], 
    "pollution": 31
  }, 
  "Nervino": {
    "coord": [
      "39.8207", 
      "-120.354"
    ], 
    "pollution": 41
  }, 
  "Shafter-Minter Field": {
    "coord": [
      "35.5059", 
      "-119.192"
    ], 
    "pollution": 117
  }, 
  "Fresno-Chandler Downtow": {
    "coord": [
      "36.7344", 
      "-119.825"
    ], 
    "pollution": 65
  }, 
  "Palmdale Prodn Flt/Test": {
    "coord": [
      "34.6328", 
      "-118.113"
    ], 
    "pollution": 162
  }, 
  "Watsonville Muni": {
    "coord": [
      "36.9357", 
      "-121.790"
    ], 
    "pollution": 375
  }, 
  "SPAULDING": {
    "coord": [
      "40.6503", 
      "-120.769"
    ], 
    "pollution": 7
  }, 
  "Gnoss Field": {
    "coord": [
      "38.1435", 
      "-122.557"
    ], 
    "pollution": 389
  }, 
  "Truckee-Tahoe": {
    "coord": [
      "39.3200", 
      "-120.140"
    ], 
    "pollution": 91
  }, 
  "Tracy Muni": {
    "coord": [
      "37.6891", 
      "-121.442"
    ], 
    "pollution": 163
  }, 
  "El Monte": {
    "coord": [
      "34.0861", 
      "-118.035"
    ], 
    "pollution": 251
  }, 
  "Fall River Mills": {
    "coord": [
      "41.0188", 
      "-121.433"
    ], 
    "pollution": 15
  }, 
  "Kern Valley": {
    "coord": [
      "35.7283", 
      "-118.420"
    ], 
    "pollution": 30
  }, 
  "March Air Force Base": {
    "coord": [
      "33.8806", 
      "-117.259"
    ], 
    "pollution": 69
  }, 
  "Barstow-Daggett": {
    "coord": [
      "34.8513", 
      "-116.798"
    ], 
    "pollution": 179
  }, 
  "Healdsburg Muni": {
    "coord": [
      "38.6535", 
      "-122.899"
    ], 
    "pollution": 70
  }, 
  "Jack Mc Namara Field": {
    "coord": [
      "41.7802", 
      "-124.237"
    ], 
    "pollution": 36
  }, 
  "LODI AIRPARK": {
    "coord": [
      "38.0841", 
      "-121.316"
    ], 
    "pollution": 34
  }, 
  "Woodlake": {
    "coord": [
      "36.3988", 
      "-119.107"
    ], 
    "pollution": 29
  }, 
  "Lonnie Pool Field/Weave": {
    "coord": [
      "40.7457", 
      "-122.922"
    ], 
    "pollution": 36
  }, 
  "Hesperia": {
    "coord": [
      "34.3772", 
      "-117.316"
    ], 
    "pollution": 15
  }, 
  "Los Angeles International": {
    "coord": [
      "33.9425", 
      "-118.408"
    ], 
    "pollution": 13079
  }, 
  "Rancho Murieta": {
    "coord": [
      "38.4888", 
      "-121.102"
    ], 
    "pollution": 67
  }, 
  "SONOMA SKYPARK": {
    "coord": [
      "38.2574", 
      "-122.434"
    ], 
    "pollution": 23
  }, 
  "Los Banos Muni": {
    "coord": [
      "37.0629", 
      "-120.869"
    ], 
    "pollution": 45
  }, 
  "Siskiyou County": {
    "coord": [
      "41.7814", 
      "-122.468"
    ], 
    "pollution": 36
  }, 
  "CONOVER AIR LODGE": {
    "coord": [
      "34.7611", 
      "-119.059"
    ], 
    "pollution": 7
  }, 
  "Ruth": {
    "coord": [
      "40.2113", 
      "-123.298"
    ], 
    "pollution": 17
  }, 
  "Flabob": {
    "coord": [
      "33.9897", 
      "-117.411"
    ], 
    "pollution": 105
  }, 
  "Burbank-Glendale-Pasadena Airport": {
    "coord": [
      "34.2006", 
      "-118.358"
    ], 
    "pollution": 1407
  }, 
  "Sacramento Internationa": {
    "coord": [
      "38.6837", 
      "-121.602"
    ], 
    "pollution": 2440
  }, 
  "BOHUNK'S AIRPARK": {
    "coord": [
      "34.6947", 
      "-118.283"
    ], 
    "pollution": 5
  }, 
  "BORGES - CLARKSBURG": {
    "coord": [
      "38.4432", 
      "-121.509"
    ], 
    "pollution": 7
  }, 
  "Hemet-Ryan": {
    "coord": [
      "33.7339", 
      "-117.022"
    ], 
    "pollution": 188
  }, 
  "Fullerton Muni": {
    "coord": [
      "33.8719", 
      "-117.980"
    ], 
    "pollution": 197
  }, 
  "NEW JERUSALEM": {
    "coord": [
      "37.6778", 
      "-121.301"
    ], 
    "pollution": 11
  }, 
  "CHIRIACO SUMMIT": {
    "coord": [
      "33.6649", 
      "-115.710"
    ], 
    "pollution": 14
  }, 
  "ROSAMOND SKYPARK": {
    "coord": [
      "34.8705", 
      "-118.205"
    ], 
    "pollution": 42
  }, 
  "SELMA": {
    "coord": [
      "36.5808", 
      "-119.657"
    ], 
    "pollution": 42
  }, 
  "Perris Valley": {
    "coord": [
      "33.7608", 
      "-117.218"
    ], 
    "pollution": 89
  }, 
  "Reedley Muni": {
    "coord": [
      "36.6663", 
      "-119.450"
    ], 
    "pollution": 88
  }, 
  "Banning Muni": {
    "coord": [
      "33.9231", 
      "-116.851"
    ], 
    "pollution": 27
  }, 
  "San Bernardino Internat": {
    "coord": [
      "34.0954", 
      "-117.235"
    ], 
    "pollution": 17
  }, 
  "Monterey Peninsula": {
    "coord": [
      "36.5903", 
      "-121.857"
    ], 
    "pollution": 303
  }, 
  "Santa Paula": {
    "coord": [
      "34.3472", 
      "-119.061"
    ], 
    "pollution": 118
  }, 
  "Twentynine Palms": {
    "coord": [
      "34.1321", 
      "-115.946"
    ], 
    "pollution": 47
  }, 
  "YUCCA VALLEY": {
    "coord": [
      "34.1298", 
      "-116.407"
    ], 
    "pollution": 37
  }, 
  "Mammoth Yosemite": {
    "coord": [
      "37.6241", 
      "-118.838"
    ], 
    "pollution": 33
  }, 
  "Gillespie Field": {
    "coord": [
      "32.8277", 
      "-116.982"
    ], 
    "pollution": 792
  }, 
  "University": {
    "coord": [
      "38.5315", 
      "-121.786"
    ], 
    "pollution": 68
  }, 
  "Long Beach / Daugherty Field": {
    "coord": [
      "33.8178", 
      "-118.152"
    ], 
    "pollution": 1580
  }, 
  "Cameron Airpark": {
    "coord": [
      "38.6841", 
      "-120.987"
    ], 
    "pollution": 86
  }, 
  "Wasco-Kern County": {
    "coord": [
      "35.6197", 
      "-119.354"
    ], 
    "pollution": 27
  }, 
  "Arcata": {
    "coord": [
      "40.9781", 
      "-124.109"
    ], 
    "pollution": 265
  }, 
  "Lake Tahoe": {
    "coord": [
      "38.8939", 
      "-119.995"
    ], 
    "pollution": 72
  }, 
  "EUREKA MUNI": {
    "coord": [
      "40.7809", 
      "-124.212"
    ], 
    "pollution": 6
  }, 
  "Lampson Field": {
    "coord": [
      "38.9902", 
      "-122.900"
    ], 
    "pollution": 200
  }, 
  "Round Valley": {
    "coord": [
      "39.7902", 
      "-123.266"
    ], 
    "pollution": 18
  }, 
  "Santa Maria Pub/Capt G": {
    "coord": [
      "34.8943", 
      "-120.469"
    ], 
    "pollution": 207
  }, 
  "Nut Tree": {
    "coord": [
      "38.3768", 
      "-121.962"
    ], 
    "pollution": 230
  }, 
  "Madera Muni": {
    "coord": [
      "36.9857", 
      "-120.112"
    ], 
    "pollution": 132
  }, 
  "Mc Clellan-Palomar": {
    "coord": [
      "33.1283", 
      "-117.280"
    ], 
    "pollution": 607
  }, 
  "Montgomery Field": {
    "coord": [
      "32.8150", 
      "-117.146"
    ], 
    "pollution": 728
  }, 
  "Brown Field Muni": {
    "coord": [
      "32.5723", 
      "-116.994"
    ], 
    "pollution": 371
  }, 
  "Marina Municipal": {
    "coord": [
      "36.6819", 
      "-121.762"
    ], 
    "pollution": 113
  }, 
  "Cedarville": {
    "coord": [
      "41.5527", 
      "-120.166"
    ], 
    "pollution": 11
  }, 
  "Gustine": {
    "coord": [
      "37.2627", 
      "-120.963"
    ], 
    "pollution": 20
  }, 
  "Happy Camp": {
    "coord": [
      "41.7907", 
      "-123.389"
    ], 
    "pollution": 15
  }, 
  "Livermore Muni": {
    "coord": [
      "37.6934", 
      "-121.820"
    ], 
    "pollution": 514
  }, 
  "Riverside Muni": {
    "coord": [
      "33.9519", 
      "-117.445"
    ], 
    "pollution": 211
  }, 
  "Rio Vista Muni": {
    "coord": [
      "38.1935", 
      "-121.702"
    ], 
    "pollution": 99
  }, 
  "Gansner Field": {
    "coord": [
      "39.9438", 
      "-120.947"
    ], 
    "pollution": 34
  }, 
  "Palo Alto Arpt Of Santa": {
    "coord": [
      "37.4611", 
      "-122.115"
    ], 
    "pollution": 542
  }, 
  "John Wayne-Orange County Airport": {
    "coord": [
      "33.6756", 
      "-117.868"
    ], 
    "pollution": 2502
  }, 
  "Reid-Hillview Of Santa": {
    "coord": [
      "37.3329", 
      "-121.820"
    ], 
    "pollution": 434
  }, 
  "Nevada County Air Park": {
    "coord": [
      "39.2240", 
      "-121.003"
    ], 
    "pollution": 66
  }, 
  "Trona": {
    "coord": [
      "35.8125", 
      "-117.327"
    ], 
    "pollution": 18
  }, 
  "Lee Vining": {
    "coord": [
      "37.9583", 
      "-119.107"
    ], 
    "pollution": 8
  }, 
  "Boonville": {
    "coord": [
      "39.0127", 
      "-123.383"
    ], 
    "pollution": 11
  }, 
  "Travis AFB Airport": {
    "coord": [
      "38.2627", 
      "-121.927"
    ], 
    "pollution": 21
  }, 
  "MOUNTAIN VALLEY": {
    "coord": [
      "35.1011", 
      "-118.423"
    ], 
    "pollution": 138
  }, 
  "Bakersfield Municipal": {
    "coord": [
      "35.3248", 
      "-118.996"
    ], 
    "pollution": 70
  }, 
  "Point Mugu Nas (Naval B": {
    "coord": [
      "34.1203", 
      "-119.121"
    ], 
    "pollution": 914
  }, 
  "Lompoc": {
    "coord": [
      "34.6656", 
      "-120.467"
    ], 
    "pollution": 79
  }, 
  "Taft-Kern County": {
    "coord": [
      "35.1411", 
      "-119.441"
    ], 
    "pollution": 28
  }, 
  "COMMODORE CENTER": {
    "coord": [
      "37.8791", 
      "-122.514"
    ], 
    "pollution": 13
  }, 
  "Angwin-Parrett Field": {
    "coord": [
      "38.5785", 
      "-122.435"
    ], 
    "pollution": 31
  }, 
  "Stockton Metropolitan": {
    "coord": [
      "37.9011", 
      "-121.252"
    ], 
    "pollution": 212
  }, 
  "Santa Barbara Muni": {
    "coord": [
      "34.4277", 
      "-119.852"
    ], 
    "pollution": 486
  }, 
  "Franklin Field": {
    "coord": [
      "38.3049", 
      "-121.430"
    ], 
    "pollution": 89
  }, 
  "South County Arpt Of Sa": {
    "coord": [
      "37.0816", 
      "-121.597"
    ], 
    "pollution": 132
  }, 
  "Red Bluff Muni": {
    "coord": [
      "40.1507", 
      "-122.252"
    ], 
    "pollution": 65
  }, 
  "Firebaugh": {
    "coord": [
      "36.8600", 
      "-120.464"
    ], 
    "pollution": 26
  }, 
  "Oceanside Muni": {
    "coord": [
      "33.2180", 
      "-117.352"
    ], 
    "pollution": 47
  }, 
  "Sequoia Field": {
    "coord": [
      "36.4486", 
      "-119.319"
    ], 
    "pollution": 34
  }, 
  "Weed": {
    "coord": [
      "41.4749", 
      "-122.453"
    ], 
    "pollution": 41
  }, 
  "Fallbrook Community Air": {
    "coord": [
      "33.3542", 
      "-117.251"
    ], 
    "pollution": 86
  }, 
  "Turlock Muni": {
    "coord": [
      "37.4874", 
      "-120.697"
    ], 
    "pollution": 27
  }, 
  "Cloverdale Muni": {
    "coord": [
      "38.7760", 
      "-122.993"
    ], 
    "pollution": 28
  }, 
  "Rogers Field": {
    "coord": [
      "40.2824", 
      "-121.241"
    ], 
    "pollution": 40
  }, 
  "Paradise Skypark": {
    "coord": [
      "39.7096", 
      "-121.616"
    ], 
    "pollution": 35
  }, 
  "Van Nuys": {
    "coord": [
      "34.2097", 
      "-118.490"
    ], 
    "pollution": 1132
  }, 
  "Redlands Muni": {
    "coord": [
      "34.0853", 
      "-117.146"
    ], 
    "pollution": 109
  }, 
  "Placerville": {
    "coord": [
      "38.7242", 
      "-120.753"
    ], 
    "pollution": 168
  }, 
  "Ells Field-Willits Muni": {
    "coord": [
      "39.4513", 
      "-123.372"
    ], 
    "pollution": 12
  }, 
  "Oakdale": {
    "coord": [
      "37.7564", 
      "-120.800"
    ], 
    "pollution": 50
  }, 
  "Imperial County": {
    "coord": [
      "32.8342", 
      "-115.579"
    ], 
    "pollution": 208
  }, 
  "Delano Muni": {
    "coord": [
      "35.7456", 
      "-119.237"
    ], 
    "pollution": 49
  }, 
  "EL MIRAGE FIELD ADELANTO": {
    "coord": [
      "34.6250", 
      "-117.605"
    ], 
    "pollution": 7
  }, 
  "Sutter County": {
    "coord": [
      "39.1266", 
      "-121.609"
    ], 
    "pollution": 56
  }, 
  "THE SEA RANCH": {
    "coord": [
      "38.7046", 
      "-123.433"
    ], 
    "pollution": 25
  }, 
  "Sonoma County": {
    "coord": [
      "38.5032", 
      "-122.821"
    ], 
    "pollution": 334
  }, 
  "SAN RAFAEL": {
    "coord": [
      "38.0169", 
      "-122.521"
    ], 
    "pollution": 18
  }, 
  "Susanville Muni": {
    "coord": [
      "40.3768", 
      "-120.573"
    ], 
    "pollution": 27
  }, 
  "Chemehuevi Valley": {
    "coord": [
      "34.5275", 
      "-114.431"
    ], 
    "pollution": 10
  }, 
  "Santa Ynez": {
    "coord": [
      "34.6068", 
      "-120.076"
    ], 
    "pollution": 79
  }, 
  "Camarillo": {
    "coord": [
      "34.2138", 
      "-119.094"
    ], 
    "pollution": 568
  }, 
  "Castle": {
    "coord": [
      "37.3805", 
      "-120.568"
    ], 
    "pollution": 407
  }, 
  "California City Muni": {
    "coord": [
      "35.1513", 
      "-118.017"
    ], 
    "pollution": 106
  }, 
  "Hayward Executive": {
    "coord": [
      "37.6619", 
      "-122.130"
    ], 
    "pollution": 468
  }, 
  "HYAMPOM": {
    "coord": [
      "40.6256", 
      "-123.469"
    ], 
    "pollution": 5
  }, 
  "Rohnerville": {
    "coord": [
      "40.5539", 
      "-124.133"
    ], 
    "pollution": 71
  }, 
  "Hayfork": {
    "coord": [
      "40.5471", 
      "-123.182"
    ], 
    "pollution": 44
  }, 
  "Catalina": {
    "coord": [
      "33.4050", 
      "-118.416"
    ], 
    "pollution": 59
  }, 
  "Inyokern": {
    "coord": [
      "35.6588", 
      "-117.830"
    ], 
    "pollution": 142
  }, 
  "Santa Monica Muni": {
    "coord": [
      "34.0158", 
      "-118.451"
    ], 
    "pollution": 370
  }, 
  "KINGDON AIRPARK": {
    "coord": [
      "38.0916", 
      "-121.359"
    ], 
    "pollution": 43
  }, 
  "Yuba County": {
    "coord": [
      "39.0978", 
      "-121.570"
    ], 
    "pollution": 146
  }, 
  "Paso Robles Muni": {
    "coord": [
      "35.6729", 
      "-120.627"
    ], 
    "pollution": 91
  }, 
  "Bermuda Dunes": {
    "coord": [
      "33.7484", 
      "-116.275"
    ], 
    "pollution": 96
  }, 
  "Byron": {
    "coord": [
      "37.8285", 
      "-121.626"
    ], 
    "pollution": 67
  }, 
  "Oxnard": {
    "coord": [
      "34.2008", 
      "-119.207"
    ], 
    "pollution": 335
  }, 
  "Garberville": {
    "coord": [
      "40.0860", 
      "-123.814"
    ], 
    "pollution": 39
  }, 
  "Ukiah Muni": {
    "coord": [
      "39.1260", 
      "-123.201"
    ], 
    "pollution": 102
  }, 
  "Torrance / Zamperini Field": {
    "coord": [
      "33.8033", 
      "-118.340"
    ], 
    "pollution": 481
  }, 
  "New Coalinga Muni": {
    "coord": [
      "36.1631", 
      "-120.294"
    ], 
    "pollution": 6
  }, 
  "Petaluma Muni": {
    "coord": [
      "38.2578", 
      "-122.606"
    ], 
    "pollution": 139
  }, 
  "San Francisco Internati": {
    "coord": [
      "37.6265", 
      "-122.395"
    ], 
    "pollution": 7574
  }, 
  "Redding Muni": {
    "coord": [
      "40.5119", 
      "-122.297"
    ], 
    "pollution": 220
  }, 
  "Columbia": {
    "coord": [
      "38.0304", 
      "-120.415"
    ], 
    "pollution": 119
  }, 
  "Fresno Yosemite Interna": {
    "coord": [
      "36.7802", 
      "-119.732"
    ], 
    "pollution": 813
  }, 
  "ELK GROVE": {
    "coord": [
      "38.3924", 
      "-121.331"
    ], 
    "pollution": 72
  }, 
  "OCEAN RIDGE": {
    "coord": [
      "38.8016", 
      "-123.531"
    ], 
    "pollution": 14
  }, 
  "Southern California Log": {
    "coord": [
      "34.5955", 
      "-117.383"
    ], 
    "pollution": 266
  }, 
  "Buchanan Field": {
    "coord": [
      "37.9830", 
      "-122.063"
    ], 
    "pollution": 280
  }, 
  "San Luis County Regiona": {
    "coord": [
      "35.2367", 
      "-120.650"
    ], 
    "pollution": 322
  }, 
  "Sacramento Executive": {
    "coord": [
      "38.5058", 
      "-121.502"
    ], 
    "pollution": 286
  }, 
  "RIEGO FLIGHT STRIP": {
    "coord": [
      "38.7541", 
      "-121.563"
    ], 
    "pollution": 26
  }, 
  "Hawthorne / Jack Northrop Field": {
    "coord": [
      "33.9228", 
      "-118.335"
    ], 
    "pollution": 164
  }, 
  "Meadows Field": {
    "coord": [
      "35.4461", 
      "-119.072"
    ], 
    "pollution": 422
  }, 
  "Borrego Valley": {
    "coord": [
      "33.2590", 
      "-116.321"
    ], 
    "pollution": 57
  }, 
  "DOS PALOS": {
    "coord": [
      "36.9624", 
      "-120.630"
    ], 
    "pollution": 27
  }, 
  "Auburn Muni": {
    "coord": [
      "38.9548", 
      "-121.082"
    ], 
    "pollution": 158
  }, 
  "Bryant Field": {
    "coord": [
      "38.2624", 
      "-119.226"
    ], 
    "pollution": 8
  }, 
  "Georgetown": {
    "coord": [
      "38.9211", 
      "-120.865"
    ], 
    "pollution": 58
  }, 
  "Willows-Glenn County": {
    "coord": [
      "39.5164", 
      "-122.218"
    ], 
    "pollution": 73
  }, 
  "Agua Dulce Airpark": {
    "coord": [
      "34.5042", 
      "-118.313"
    ], 
    "pollution": 7
  }, 
  "Yolo County-Davis/Woodl": {
    "coord": [
      "38.5791", 
      "-121.857"
    ], 
    "pollution": 149
  }, 
  "Ramona": {
    "coord": [
      "33.0389", 
      "-116.914"
    ], 
    "pollution": 406
  }, 
  "Corona Muni": {
    "coord": [
      "33.8978", 
      "-117.603"
    ], 
    "pollution": 178
  }, 
  "Mariposa-Yosemite": {
    "coord": [
      "37.5108", 
      "-120.042"
    ], 
    "pollution": 82
  }, 
  "Sacramento Mather": {
    "coord": [
      "38.5539", 
      "-121.298"
    ], 
    "pollution": 454
  }, 
  "SIERRA SKY PARK": {
    "coord": [
      "36.8402", 
      "-119.869"
    ], 
    "pollution": 32
  }, 
  "Mefford Field": {
    "coord": [
      "36.1563", 
      "-119.326"
    ], 
    "pollution": 74
  }, 
  "Trinity Center": {
    "coord": [
      "40.9832", 
      "-122.694"
    ], 
    "pollution": 44
  }, 
  "Furnace Creek": {
    "coord": [
      "36.4638", 
      "-116.881"
    ], 
    "pollution": 28
  }, 
  "Mesa Del Rey": {
    "coord": [
      "36.2280", 
      "-121.122"
    ], 
    "pollution": 8
  }, 
  "Lincoln Regional/Karl H": {
    "coord": [
      "38.9171", 
      "-121.354"
    ], 
    "pollution": 170
  }, 
  "Rio Linda": {
    "coord": [
      "38.6760", 
      "-121.446"
    ], 
    "pollution": 134
  }, 
  "Butte Valley": {
    "coord": [
      "41.8871", 
      "-121.976"
    ], 
    "pollution": 5
  }, 
  "Visalia Muni": {
    "coord": [
      "36.3187", 
      "-119.393"
    ], 
    "pollution": 107
  }, 
  "Mc Clellan Airfield": {
    "coord": [
      "38.6676", 
      "-121.401"
    ], 
    "pollution": 42
  }, 
  "FRAZIER LAKE AIRPARK": {
    "coord": [
      "36.9533", 
      "-121.466"
    ], 
    "pollution": 13
  }, 
  "ECKERT FIELD": {
    "coord": [
      "36.1624", 
      "-119.051"
    ], 
    "pollution": 10
  }, 
  "French Valley": {
    "coord": [
      "33.5761", 
      "-117.128"
    ], 
    "pollution": 255
  }, 
  "Corning Muni": {
    "coord": [
      "39.9438", 
      "-122.171"
    ], 
    "pollution": 15
  }, 
  "Half Moon Bay": {
    "coord": [
      "37.5138", 
      "-122.501"
    ], 
    "pollution": 170
  }, 
  "Modesto City-Co-Harry S": {
    "coord": [
      "37.6297", 
      "-120.966"
    ], 
    "pollution": 224
  }, 
  "Porterville Muni": {
    "coord": [
      "36.0296", 
      "-119.063"
    ], 
    "pollution": 113
  }, 
  "HARRIS RANCH": {
    "coord": [
      "36.2481", 
      "-120.239"
    ], 
    "pollution": 26
  }, 
  "Haigh Field": {
    "coord": [
      "39.7212", 
      "-122.147"
    ], 
    "pollution": 48
  }, 
  "Kneeland": {
    "coord": [
      "40.7193", 
      "-123.928"
    ], 
    "pollution": 23
  }, 
  "Merced Municipal/Macrea": {
    "coord": [
      "37.2847", 
      "-120.514"
    ], 
    "pollution": 267
  }, 
  "Palm Springs Regional": {
    "coord": [
      "33.8271", 
      "-116.511"
    ], 
    "pollution": 453
  }, 
  "Mojave": {
    "coord": [
      "35.0594", 
      "-118.152"
    ], 
    "pollution": 63
  }, 
  "Calaveras Co-Maury Rasm": {
    "coord": [
      "38.1461", 
      "-120.648"
    ], 
    "pollution": 59
  }, 
  "Hollister Muni": {
    "coord": [
      "36.8934", 
      "-121.410"
    ], 
    "pollution": 144
  }, 
  "Desert Resorts Regional": {
    "coord": [
      "33.6279", 
      "-116.160"
    ], 
    "pollution": 195
  }, 
  "Salinas Muni": {
    "coord": [
      "36.6626", 
      "-121.619"
    ], 
    "pollution": 234
  }, 
  "VANDENBERG AFB": {
    "coord": [
      "34.7297", 
      "-120.577"
    ], 
    "pollution": 21
  }, 
  "General Wm J Fox Airfie": {
    "coord": [
      "34.7410", 
      "-118.219"
    ], 
    "pollution": 173
  }, 
  "Holtville": {
    "coord": [
      "32.8403", 
      "-115.267"
    ], 
    "pollution": 8
  }, 
  "Lost Hills-Kern County": {
    "coord": [
      "35.6236", 
      "-119.686"
    ], 
    "pollution": 9
  }, 
  "Bishop": {
    "coord": [
      "37.3731", 
      "-118.364"
    ], 
    "pollution": 78
  }, 
  "Brackett Field": {
    "coord": [
      "34.0917", 
      "-117.782"
    ], 
    "pollution": 360
  }, 
  "SONOMA VALLEY": {
    "coord": [
      "38.2239", 
      "-122.450"
    ], 
    "pollution": 27
  }, 
  "Alturas Muni": {
    "coord": [
      "41.4830", 
      "-120.565"
    ], 
    "pollution": 81
  }, 
  "Mendota": {
    "coord": [
      "36.7580", 
      "-120.371"
    ], 
    "pollution": 24
  }, 
  "Watts-Woodland": {
    "coord": [
      "38.6739", 
      "-121.872"
    ], 
    "pollution": 63
  }, 
  "Chowchilla": {
    "coord": [
      "37.1124", 
      "-120.247"
    ], 
    "pollution": 19
  }, 
  "Napa County": {
    "coord": [
      "38.2088", 
      "-122.289"
    ], 
    "pollution": 356
  }, 
  "Lone Pine": {
    "coord": [
      "36.5883", 
      "-118.052"
    ], 
    "pollution": 22
  }
}
